[
  { "name": "exp_h64_l6_th4_xy4_lr5e-4_clip0.5", "epochs": 3, "batch_size": 65536, "hidden": 64, "layers": 6, "time_harmonics": 4, "xy_harmonics": 4, "xy_include_input": true, "lr": 5e-4, "weight_decay": 1e-5, "clip_grad": 0.5, "residual_mode": true, "baseline_time": 12, "seed": 42, "omp_threads": 7 },
  { "name": "exp_h64_l6_th4_xy4_lr5e-4_clip1.0", "epochs": 3, "batch_size": 65536, "hidden": 64, "layers": 6, "time_harmonics": 4, "xy_harmonics": 4, "xy_include_input": true, "lr": 5e-4, "weight_decay": 1e-5, "clip_grad": 1.0, "residual_mode": true, "baseline_time": 12, "seed": 42, "omp_threads": 7 },
  { "name": "exp_h64_l6_th4_xy4_lr1e-3_clip0.5", "epochs": 3, "batch_size": 65536, "hidden": 64, "layers": 6, "time_harmonics": 4, "xy_harmonics": 4, "xy_include_input": true, "lr": 1e-3, "weight_decay": 1e-5, "clip_grad": 0.5, "residual_mode": true, "baseline_time": 12, "seed": 42, "omp_threads": 7 },
  { "name": "exp_h64_l6_th4_xy4_lr1e-3_clip1.0", "epochs": 3, "batch_size": 65536, "hidden": 64, "layers": 6, "time_harmonics": 4, "xy_harmonics": 4, "xy_include_input": true, "lr": 1e-3, "weight_decay": 1e-5, "clip_grad": 1.0, "residual_mode": true, "baseline_time": 12, "seed": 42, "omp_threads": 7 },
  { "name": "exp_h64_l6_th4_xy4_lr3e-4_clip0.5", "epochs": 3, "batch_size": 65536, "hidden": 64, "layers": 6, "time_harmonics": 4, "xy_harmonics": 4, "xy_include_input": true, "lr": 3e-4, "weight_decay": 1e-5, "clip_grad": 0.5, "residual_mode": true, "baseline_time": 12, "seed": 42, "omp_threads": 7 },
  { "name": "exp_h64_l6_th4_xy4_lr3e-4_clip1.0", "epochs": 3, "batch_size": 65536, "hidden": 64, "layers": 6, "time_harmonics": 4, "xy_harmonics": 4, "xy_include_input": true, "lr": 3e-4, "weight_decay": 1e-5, "clip_grad": 1.0, "residual_mode": true, "baseline_time": 12, "seed": 42, "omp_threads": 7 },

  { "name": "exp_h64_l8_th4_xy4_lr5e-4_clip0.5", "epochs": 3, "batch_size": 65536, "hidden": 64, "layers": 8, "time_harmonics": 4, "xy_harmonics": 4, "xy_include_input": true, "lr": 5e-4, "weight_decay": 1e-5, "clip_grad": 0.5, "residual_mode": true, "baseline_time": 12, "seed": 42, "omp_threads": 7 },
  { "name": "exp_h64_l8_th4_xy4_lr5e-4_clip1.0", "epochs": 3, "batch_size": 65536, "hidden": 64, "layers": 8, "time_harmonics": 4, "xy_harmonics": 4, "xy_include_input": true, "lr": 5e-4, "weight_decay": 1e-5, "clip_grad": 1.0, "residual_mode": true, "baseline_time": 12, "seed": 42, "omp_threads": 7 },
  { "name": "exp_h64_l8_th4_xy4_lr1e-3_clip0.5", "epochs": 3, "batch_size": 65536, "hidden": 64, "layers": 8, "time_harmonics": 4, "xy_harmonics": 4, "xy_include_input": true, "lr": 1e-3, "weight_decay": 1e-5, "clip_grad": 0.5, "residual_mode": true, "baseline_time": 12, "seed": 42, "omp_threads": 7 },
  { "name": "exp_h64_l8_th4_xy4_lr1e-3_clip1.0", "epochs": 3, "batch_size": 65536, "hidden": 64, "layers": 8, "time_harmonics": 4, "xy_harmonics": 4, "xy_include_input": true, "lr": 1e-3, "weight_decay": 1e-5, "clip_grad": 1.0, "residual_mode": true, "baseline_time": 12, "seed": 42, "omp_threads": 7 },
  { "name": "exp_h64_l8_th4_xy4_lr3e-4_clip0.5", "epochs": 3, "batch_size": 65536, "hidden": 64, "layers": 8, "time_harmonics": 4, "xy_harmonics": 4, "xy_include_input": true, "lr": 3e-4, "weight_decay": 1e-5, "clip_grad": 0.5, "residual_mode": true, "baseline_time": 12, "seed": 42, "omp_threads": 7 },
  { "name": "exp_h64_l8_th4_xy4_lr3e-4_clip1.0", "epochs": 3, "batch_size": 65536, "hidden": 64, "layers": 8, "time_harmonics": 4, "xy_harmonics": 4, "xy_include_input": true, "lr": 3e-4, "weight_decay": 1e-5, "clip_grad": 1.0, "residual_mode": true, "baseline_time": 12, "seed": 42, "omp_threads": 7 },

  { "name": "exp_h96_l6_th4_xy4_lr5e-4_clip0.5", "epochs": 3, "batch_size": 65536, "hidden": 96, "layers": 6, "time_harmonics": 4, "xy_harmonics": 4, "xy_include_input": true, "lr": 5e-4, "weight_decay": 1e-5, "clip_grad": 0.5, "residual_mode": true, "baseline_time": 12, "seed": 42, "omp_threads": 7 },
  { "name": "exp_h96_l6_th4_xy4_lr5e-4_clip1.0", "epochs": 3, "batch_size": 65536, "hidden": 96, "layers": 6, "time_harmonics": 4, "xy_harmonics": 4, "xy_include_input": true, "lr": 5e-4, "weight_decay": 1e-5, "clip_grad": 1.0, "residual_mode": true, "baseline_time": 12, "seed": 42, "omp_threads": 7 },
  { "name": "exp_h96_l6_th4_xy4_lr1e-3_clip0.5", "epochs": 3, "batch_size": 65536, "hidden": 96, "layers": 6, "time_harmonics": 4, "xy_harmonics": 4, "xy_include_input": true, "lr": 1e-3, "weight_decay": 1e-5, "clip_grad": 0.5, "residual_mode": true, "baseline_time": 12, "seed": 42, "omp_threads": 7 },
  { "name": "exp_h96_l6_th4_xy4_lr1e-3_clip1.0", "epochs": 3, "batch_size": 65536, "hidden": 96, "layers": 6, "time_harmonics": 4, "xy_harmonics": 4, "xy_include_input": true, "lr": 1e-3, "weight_decay": 1e-5, "clip_grad": 1.0, "residual_mode": true, "baseline_time": 12, "seed": 42, "omp_threads": 7 },
  { "name": "exp_h96_l6_th4_xy4_lr3e-4_clip0.5", "epochs": 3, "batch_size": 65536, "hidden": 96, "layers": 6, "time_harmonics": 4, "xy_harmonics": 4, "xy_include_input": true, "lr": 3e-4, "weight_decay": 1e-5, "clip_grad": 0.5, "residual_mode": true, "baseline_time": 12, "seed": 42, "omp_threads": 7 },
  { "name": "exp_h96_l6_th4_xy4_lr3e-4_clip1.0", "epochs": 3, "batch_size": 65536, "hidden": 96, "layers": 6, "time_harmonics": 4, "xy_harmonics": 4, "xy_include_input": true, "lr": 3e-4, "weight_decay": 1e-5, "clip_grad": 1.0, "residual_mode": true, "baseline_time": 12, "seed": 42, "omp_threads": 7 },

  { "name": "exp_h128_l6_th4_xy4_lr5e-4_clip0.5", "epochs": 3, "batch_size": 65536, "hidden": 128, "layers": 6, "time_harmonics": 4, "xy_harmonics": 4, "xy_include_input": true, "lr": 5e-4, "weight_decay": 1e-5, "clip_grad": 0.5, "residual_mode": true, "baseline_time": 12, "seed": 42, "omp_threads": 7 },
  { "name": "exp_h128_l6_th4_xy4_lr5e-4_clip1.0", "epochs": 3, "batch_size": 65536, "hidden": 128, "layers": 6, "time_harmonics": 4, "xy_harmonics": 4, "xy_include_input": true, "lr": 5e-4, "weight_decay": 1e-5, "clip_grad": 1.0, "residual_mode": true, "baseline_time": 12, "seed": 42, "omp_threads": 7 },
  { "name": "exp_h128_l6_th4_xy4_lr1e-3_clip0.5", "epochs": 3, "batch_size": 65536, "hidden": 128, "layers": 6, "time_harmonics": 4, "xy_harmonics": 4, "xy_include_input": true, "lr": 1e-3, "weight_decay": 1e-5, "clip_grad": 0.5, "residual_mode": true, "baseline_time": 12, "seed": 42, "omp_threads": 7 },
  { "name": "exp_h128_l6_th4_xy4_lr1e-3_clip1.0", "epochs": 3, "batch_size": 65536, "hidden": 128, "layers": 6, "time_harmonics": 4, "xy_harmonics": 4, "xy_include_input": true, "lr": 1e-3, "weight_decay": 1e-5, "clip_grad": 1.0, "residual_mode": true, "baseline_time": 12, "seed": 42, "omp_threads": 7 },
  { "name": "exp_h128_l6_th4_xy4_lr3e-4_clip0.5", "epochs": 3, "batch_size": 65536, "hidden": 128, "layers": 6, "time_harmonics": 4, "xy_harmonics": 4, "xy_include_input": true, "lr": 3e-4, "weight_decay": 1e-5, "clip_grad": 0.5, "residual_mode": true, "baseline_time": 12, "seed": 42, "omp_threads": 7 },
  { "name": "exp_h128_l6_th4_xy4_lr3e-4_clip1.0", "epochs": 3, "batch_size": 65536, "hidden": 128, "layers": 6, "time_harmonics": 4, "xy_harmonics": 4, "xy_include_input": true, "lr": 3e-4, "weight_decay": 1e-5, "clip_grad": 1.0, "residual_mode": true, "baseline_time": 12, "seed": 42, "omp_threads": 7 },

  { "name": "exp_h256_l10_th6_xy4_lr5e-4_clip0.5", "epochs": 3, "batch_size": 65536, "hidden": 256, "layers": 10, "time_harmonics": 6, "xy_harmonics": 4, "xy_include_input": true, "lr": 5e-4, "weight_decay": 1e-5, "clip_grad": 0.5, "residual_mode": true, "baseline_time": 12, "seed": 42, "omp_threads": 7 },
  { "name": "exp_h256_l10_th6_xy4_lr5e-4_clip1.0", "epochs": 3, "batch_size": 65536, "hidden": 256, "layers": 10, "time_harmonics": 6, "xy_harmonics": 4, "xy_include_input": true, "lr": 5e-4, "weight_decay": 1e-5, "clip_grad": 1.0, "residual_mode": true, "baseline_time": 12, "seed": 42, "omp_threads": 7 },
  { "name": "exp_h256_l10_th6_xy4_lr1e-3_clip0.5", "epochs": 3, "batch_size": 65536, "hidden": 256, "layers": 10, "time_harmonics": 6, "xy_harmonics": 4, "xy_include_input": true, "lr": 1e-3, "weight_decay": 1e-5, "clip_grad": 0.5, "residual_mode": true, "baseline_time": 12, "seed": 42, "omp_threads": 7 },
  { "name": "exp_h256_l10_th6_xy4_lr1e-3_clip1.0", "epochs": 3, "batch_size": 65536, "hidden": 256, "layers": 10, "time_harmonics": 6, "xy_harmonics": 4, "xy_include_input": true, "lr": 1e-3, "weight_decay": 1e-5, "clip_grad": 1.0, "residual_mode": true, "baseline_time": 12, "seed": 42, "omp_threads": 7 },
  { "name": "exp_h256_l10_th6_xy4_lr3e-4_clip0.5", "epochs": 3, "batch_size": 65536, "hidden": 256, "layers": 10, "time_harmonics": 6, "xy_harmonics": 4, "xy_include_input": true, "lr": 3e-4, "weight_decay": 1e-5, "clip_grad": 0.5, "residual_mode": true, "baseline_time": 12, "seed": 42, "omp_threads": 7 },
  { "name": "exp_h256_l10_th6_xy4_lr3e-4_clip1.0", "epochs": 3, "batch_size": 65536, "hidden": 256, "layers": 10, "time_harmonics": 6, "xy_harmonics": 4, "xy_include_input": true, "lr": 3e-4, "weight_decay": 1e-5, "clip_grad": 1.0, "residual_mode": true, "baseline_time": 12, "seed": 42, "omp_threads": 7 }
]
